typhonql_mlconnector/__init__.py
typhonql_mlconnector-0.0.1.dist-info/LICENSE.txt
typhonql_mlconnector-0.0.1.dist-info/METADATA
typhonql_mlconnector-0.0.1.dist-info/WHEEL
typhonql_mlconnector-0.0.1.dist-info/top_level.txt
typhonql_mlconnector-0.0.1.dist-info/RECORD
