Metadata-Version: 2.1
Name: typhonql-mlconnector
Version: 0.0.1
Summary: typhonql-mlconnector package for queries
Home-page: https://gitlab.com/ge0rge.pap
Author: PAPAIOANNOU GEORGE
Author-email: papageorge94@gmail.com
License: UNKNOWN
Platform: UNKNOWN
Classifier: Programming Language :: Python :: 3
Classifier: License :: OSI Approved :: MIT License
Classifier: Operating System :: OS Independent
Requires-Python: >=3.6
